payit/__init__.py
payit/exceptions.py
payit/gateway.py
payit/helpers.py
payit/manager.py
payit/redirection.py
payit/transaction.py
payit/gateways/__init__.py
payit/gateways/aqayepardakht.py
payit/gateways/asanpardakht.py
payit/gateways/bahamta.py
payit/gateways/dummy.py
payit/gateways/irankish.py
payit/gateways/mellat.py
payit/gateways/parsian.py
payit/gateways/payir.py
payit/gateways/zarinpal.py
tests/__init__.py
tests/test_dummy_gateway.py
tests/test_gateway_aqayepardakht.py
tests/test_gateway_asanpardakht.py
tests/test_gateway_bahamta.py
tests/test_gateway_irankish.py
tests/test_gateway_mellat.py
tests/test_gateway_parsian.py
tests/test_gateway_payir.py
tests/test_gateway_zarinpal.py
tests/test_manager.py
tests/test_transaction.py
tests/mockup/__init__.py
tests/mockup/aqayerpardakht_gateway.py
tests/mockup/asanpardakht_gateway.py
tests/mockup/bahamta_gateway.py
tests/mockup/irankish_gateway.py
tests/mockup/mellat_gateway.py
tests/mockup/parsian_gateway.py
tests/mockup/payir_gateway.py
tests/mockup/zarinpal_gateway.py
payit-1.2.0.dist-info/LICENSE
payit-1.2.0.dist-info/METADATA
payit-1.2.0.dist-info/WHEEL
payit-1.2.0.dist-info/top_level.txt
payit-1.2.0.dist-info/RECORD
