Metadata-Version: 2.1
Name: payit
Version: 1.2.0
Summary: Online payment gateways wrapper library.
Home-page: https://github.com/meyt/payit
Author: Mahdi Ghanea.g
Author-email: UNKNOWN
License: MIT License
Platform: UNKNOWN
Classifier: Environment :: Console
Classifier: Environment :: Web Environment
Classifier: Intended Audience :: Developers
Classifier: Natural Language :: English
Classifier: Development Status :: 3 - Alpha
Classifier: License :: OSI Approved :: MIT License
Classifier: Operating System :: OS Independent
Classifier: Programming Language :: Python :: 3.5
Classifier: Programming Language :: Python :: 3.6
Classifier: Programming Language :: Python :: 3.7
Classifier: Programming Language :: Python :: 3.8
Classifier: Programming Language :: Python :: 3.9
Classifier: Topic :: Software Development
Classifier: Topic :: Software Development :: Libraries
Classifier: Topic :: Software Development :: Libraries :: Python Modules
Requires-Dist: py3rijndael (>=0.3.0)
Requires-Dist: requests (>=2.22.0)
Requires-Dist: zeep (>=3.4.0)
